MANIFEST.in
README.md
__init__.py
requirements.txt
setup.py
./__init__.py
./requirements.txt
./setup.py
./tmqc/__init__.py
./tmqc.egg-info/SOURCES.txt
./tmqc.egg-info/dependency_links.txt
./tmqc.egg-info/requires.txt
./tmqc.egg-info/top_level.txt
./tmqc/api/__init__.py
./tmqc/api/tradeApi_pb2.py
./tmqc/api/tradeApi_pb2_grpc.py
./tmqc/common/Decorator.pyd
./tmqc/common/Observer.pyd
./tmqc/common/__init__.py
./tmqc/common/balance.pyd
./tmqc/common/basefunc.pyd
./tmqc/common/basequotation.pyd
./tmqc/common/cashFlow.pyd
./tmqc/common/cht2chs.pyd
./tmqc/common/config.pyd
./tmqc/common/db.pyd
./tmqc/common/db_alc.pyd
./tmqc/common/db_mgo.pyd
./tmqc/common/db_mysql_connetor.pyd
./tmqc/common/db_pymysql.pyd
./tmqc/common/db_sqlalchemy.pyd
./tmqc/common/db_sqlite.pyd
./tmqc/common/define.pyd
./tmqc/common/file_op.pyd
./tmqc/common/income.pyd
./tmqc/common/indexData.pyd
./tmqc/common/indexData_pb2.pyd
./tmqc/common/indexData_pb2_grpc.pyd
./tmqc/common/levenshtein.pyd
./tmqc/common/log.pyd
./tmqc/common/match.pyd
./tmqc/common/match_name.pyd
./tmqc/common/pyetc.pyd
./tmqc/common/redis_db.pyd
./tmqc/common/singleInstance.pyd
./tmqc/common/site_binding.pyd
./tmqc/common/sql_cache.pyd
./tmqc/common/stock_codes.conf
./tmqc/common/stream.pyd
./tmqc/common/sys_define.pyd
./tmqc/common/text.pyd
./tmqc/common/timer.pyd
./tmqc/common/web.pyd
./tmqc/common/build/temp.win-amd64-cpython-311/Release/Decorator.cp311-win_amd64.lib
./tmqc/common/build/temp.win-amd64-cpython-311/Release/Observer.cp311-win_amd64.lib
./tmqc/common/build/temp.win-amd64-cpython-311/Release/balance.cp311-win_amd64.lib
./tmqc/common/build/temp.win-amd64-cpython-311/Release/basefunc.cp311-win_amd64.lib
./tmqc/common/build/temp.win-amd64-cpython-311/Release/basequotation.cp311-win_amd64.lib
./tmqc/common/build/temp.win-amd64-cpython-311/Release/cashFlow.cp311-win_amd64.lib
./tmqc/common/build/temp.win-amd64-cpython-311/Release/cht2chs.cp311-win_amd64.lib
./tmqc/common/build/temp.win-amd64-cpython-311/Release/config.cp311-win_amd64.lib
./tmqc/common/build/temp.win-amd64-cpython-311/Release/db.cp311-win_amd64.lib
tmqc.egg-info/PKG-INFO
tmqc.egg-info/SOURCES.txt
tmqc.egg-info/dependency_links.txt
tmqc.egg-info/not-zip-safe
tmqc.egg-info/requires.txt
tmqc.egg-info/top_level.txt
